python_deprecation_dates/__init__.py
python_deprecation_dates/python_eol_api.py
python_deprecation_dates-0.2.6.dist-info/METADATA
python_deprecation_dates-0.2.6.dist-info/WHEEL
python_deprecation_dates-0.2.6.dist-info/top_level.txt
python_deprecation_dates-0.2.6.dist-info/RECORD
